{
  "id": "2026-02-08",
  "date": "2026-02-08",
  "title": "美联储维持基准利率上限于3.75%以求货币政策稳定",
  "summary": "据本台消息，圣路易斯联储（FRED）于2026年2月8日更新的官方数据显示，美联储理事会决定将联邦基金利率目标范围的上限维持在3.75%。发回的报道显示，这一利率水平自2月初以来一直保持不变，充分反映了联邦公开市场委员会在近期会议后力求维持货币政策稳定的一贯立场。观察人士指出，在当前的宏观经济环境下，美联储此举旨在为市场提供明确的政策预期，通过维持现有的利率框架，以应对潜在的经济波动并确保金融体系的平稳运行。",
  "coverImage": "https://picsum.photos/seed/2026-02-08/800/600",
  "fullContent": "## 局势综述\n大家好，我是每日新闻频道主持人乔。很高兴能在这个充满变数的时刻，为您带来最新的全球动态。现在的国际局势可谓风云变幻，从华尔街的金融波动到新兴市场的崛起，每一条信息都可能重塑未来的经济版图。在接下来的节目中，我们将带您深入剖析过去24小时内影响全球进程的20件大事。今天的新闻焦点异常集中：美联储维持利率稳定的背后隐藏着怎样的财政博弈？金价突破5000美元大关，究竟是避险情绪的极致释放，还是货币体系动摇的预警？同时，日本政坛的新动向、印度资本市场的剧烈震荡，以及国际货币基金组织对全球增长动力的最新研判，都将是我们关注的重中之重。请紧随我们的报道，走进这一场深度的新闻调查之旅。\n\n## 重点情报\n### 1. 美联储维持基准利率上限于3.75%以求货币政策稳定\n- **时间**: 2026-02-08\n- **来源**: FRED (St. Louis Fed)\n- **摘要**: 据本台消息，圣路易斯联储（FRED）于2026年2月8日更新的官方数据显示，美联储理事会决定将联邦基金利率目标范围的上限维持在3.75%。发回的报道显示，这一利率水平自2月初以来一直保持不变，充分反映了联邦公开市场委员会在近期会议后力求维持货币政策稳定的一贯立场。观察人士指出，在当前的宏观经济环境下，美联储此举旨在为市场提供明确的政策预期，通过维持现有的利率框架，以应对潜在的经济波动并确保金融体系的平稳运行。\n- **消息来源**:\n  - [1] [FRED (St. Louis Fed)](https://fred.stlouisfed.org/series/DFEDTARU)\n\n### 2. 美联储公开市场操作转型：从减持证券转向缓慢增持\n- **时间**: 2026-02-07\n- **来源**: BPInsights\n- **摘要**: 据BPInsights发布的最新分析显示，美联储当前的货币政策操作正在发生显著变化。财政部借款咨询委员会注意到，美联储已经开始从之前的减持证券策略转向缓慢增持。与此同时，为了增强金融市场的流动性，美联储预计将增加常设回购操作的使用频率。这一政策转向被视为应对市场潜在波动的前置举措，显示出货币当局在平衡资产负债表与维持市场稳定性之间的复杂考量。本台将持续关注这一操作对全球流动性环境的深远影响。\n- **消息来源**:\n  - [1] [BPInsights](https://bpi.com/bpinsights-february-7-2026/)\n\n### 3. 洛希尔公司警告：政治压力或导致美联储独立性受损\n- **时间**: 2026-02-07\n- **来源**: Rothschild & Co\n- **摘要**: 洛希尔公司在最新的报告中发出了严厉警告。据其分析指出，尽管目前金融市场对于美联储面临的政治压力反应相对平淡，但这种潜伏的风险不容忽视。报告强调，美联储的独立性一旦受损，可能直接导致其信誉的丧失，进而引发广泛的金融不稳定。洛希尔公司的专家们建议投资者，必须警惕决策透明度受外部政治因素干预的可能性，因为这不仅关乎短期利率走向，更关乎美元在全球金融体系中的长期信用基础。\n- **消息来源**:\n  - [1] [Rothschild & Co](https://www.linkedin.com/pulse/beyond-noise-february-2026-rothschildandco-pmmae)\n\n### 4. 商业银行预期增持美债以应对监管变动与存款增长\n- **时间**: 2026-02-07\n- **来源**: Bloomberg\n- **摘要**: 据彭博社消息，随着监管环境的变动以及市场对存款增长的普遍预期，全球商业银行正准备扩大对美国国债的投资。这一动向被视为银行业在利率维持高位背景下的防御性布局。分析指出，银行机构此举不仅是为了满足资本充足率的要求，也是在当前充满不确定性的宏观环境下，寻求稳健收益的重要手段。市场观察人士普遍认为，这种大规模的资金流动可能会对美债收益率曲线产生平抑作用，并进一步改变私人部门的资产配置结构。\n- **消息来源**:\n  - [1] [Bloomberg](https://www.bloomberg.com/news/articles/2026-02-07/get-ready-for-double-whammy-of-us-jobs-and-inflation)\n\n### 5. 市场防御情绪抬头：资金加速轮动至消费必需品板块\n- **时间**: 2026-02-07\n- **来源**: Investing.com\n- **摘要**: 据Investing.com的分析师指出，2026年初的宏观经济环境依然充满不确定性，这导致全球投资者的防御性倾向显著增强。最新的资金流向数据显示，大量资本正从高风险资产轮动至消费必需品等防御性板块。分析师Charles-Henry Monchau强调，这种趋势反映了市场对稳健收益的极度追求，尤其是在利率长期维持高位且经济指标不明朗的当下。投资者普遍希望通过配置具有抗周期特性的资产，来对冲未来可能出现的剧烈经济波动。\n- **消息来源**:\n  - [1] [Investing.com](https://www.investing.com/)\n\n### 6. 日本首相高市早苗发表讲话：货币政策独立性成关注焦点\n- **时间**: 2026-02-08\n- **来源**: Japan Today\n- **摘要**: 本台东京消息，2026年2月8日，日本首相高市早苗在首相官邸举行新闻发布会。作为内阁首脑，高市早苗的政策主张被认为将对日本银行的独立性产生深远影响。据发回的报道显示，市场目前正密切关注其关于通胀目标及财政政策的最新表态。随着全球通胀压力的变化，高市早苗是否会推动日本结束长期的超宽松货币环境，或者干预日元汇率波动，已成为全球投资者研判日本未来货币政策转向的关键指标。目前，东京金融市场对此保持高度戒备。\n- **消息来源**:\n  - [1] [Japan Today](https://japantoday.com/sitemap.xml)\n\n### 7. 印度主要城市零售燃油价格在监测周期内保持平稳\n- **时间**: 2026-02-08\n- **来源**: Moneycontrol\n- **摘要**: 据Moneycontrol的最新监测数据显示，截至2026年2月8日，印度各主要城市的零售燃油价格表现出显著的稳定性。在海得拉巴，汽油价格维持在每升107.45卢比；而詹谢普尔和瓦多达拉的柴油价格也分别保持在92.53卢比和89.82卢比。数据显示，上述地区的燃料价格在过去10天内均未发生变动。这显示出在当前监测周期内，尽管国际原油市场有所波动，但印度国内的成品油零售市场仍处于相对平稳的稳定期。\n- **消息来源**:\n  - [1] [Moneycontrol](https://www.moneycontrol.com/fuel-price/telangana/petrol-price-in-hyderabad/)\n\n### 8. 黄金价格突破5000美元大关创历史新高\n- **时间**: 2026-02-08\n- **来源**: Trading Economics\n- **摘要**: 据Trading Economics的实时监测显示，全球大宗商品市场迎来历史性时刻，金价已成功突破每盎司5,000美元大关，创下历史最高纪录。发回的报道显示，这一涨势主要受到全球避险情绪升温以及对主权信用担忧的驱动。分析指出，投资者正以前所未有的速度涌入黄金市场，将其视为应对地缘政治压力和货币贬值风险的最后堡垒。随着这一关键心理价位的突破，市场正密切关注金价是否会进一步引发更大规模的避险资金流入。\n- **消息来源**:\n  - [1] [Trading Economics](https://tradingeconomics.com/commodity/silver)\n\n### 9. 白银价格年内涨幅达145%并维持高位波动\n- **时间**: 2026-02-08\n- **来源**: CBS News\n- **摘要**: 据CBS News报道，白银市场在过去24小时内继续表现活跃，目前价格维持在每盎司77.97美元的高位。尽管在经历了前期的暴涨后进入震荡期，但其较去年同期约145%的涨幅依然令市场感到震惊。发回的分析指出，白银作为工业原材料和避险资产的双重属性，在当前科技支出增长和全球地缘政治压力交织的背景下得到了极致体现。目前，白银市场的波动性依然显著高于黄金，投资者正审慎评估其未来的走势空间。\n- **消息来源**:\n  - [1] [CBS News](https://tradingeconomics.com/commodity/silver)\n\n### 10. 道琼斯指数历史性收于50000点上方\n- **时间**: 2026-02-08\n- **来源**: Economic Times\n- **摘要**: 据Economic Times报道，在AI产业支出增长及科技股强劲反弹的推动下，道琼斯工业平均指数在2026年2月8日首次收于50,000点上方，标志着美国股市进入了一个新的纪元。尽管宏观经济环境存在诸多变数，但科技领头羊的表现依然支撑了投资者的信心。分析指出，由于全球企业在人工智能领域的持续投入，相关产业链的收益预期显著提升。然而，也有专家提醒，在指数触及这一关键里程碑后，需警惕短期内可能出现的获利盘回吐压力。\n- **消息来源**:\n  - [1] [Economic Times](https://tradingeconomics.com/commodity/silver)\n\n### 11. 全球原油市场维持宽幅震荡态势\n- **时间**: 2026-02-08\n- **来源**: Trading Economics\n- **摘要**: 据Trading Economics最新发布的数据，全球能源市场在过去24小时内保持了震荡态势。截至2026年2月8日，WTI原油期货价格报每桶63.55美元，而布伦特原油则报每桶68.05美元。报道显示，油价目前受到多重因素的影响，包括全球经济增长放缓的预期以及对潜在关税威胁的担忧。分析师认为，供需关系的微妙平衡以及地缘政治风险的起伏，使得油价在短期内难以形成明显的单边突破，市场正处于观望主要产油国下一步动作的等待期。\n- **消息来源**:\n  - [1] [Trading Economics](https://tradingeconomics.com/commodity/silver)\n\n### 12. IMF总裁称新兴市场已占全球GDP 56%以上\n- **时间**: 2026-02-08\n- **来源**: Arab News\n- **摘要**: 据本台综合报道，国际货币基金组织（IMF）总裁格奥尔基耶娃在沙特举行的新兴市场会议上发表重要讲话。她指出，新兴市场目前已占全球GDP的56%以上，无可争议地成为全球经济增长的主要动力。格奥尔基耶娃强调，新兴经济体的这种崛起正在重塑全球经济版图，但同时也面临着前所未有的挑战。她呼吁各国应进一步加强政策协调，以应对日益复杂的全球贸易环境和金融市场波动。这一表态凸显了IMF对新兴市场在全球治理中发挥更大作用的期待。\n- **消息来源**:\n  - [1] [Arab News](https://www.arabnews.com/node/2632181/business-economy)\n\n### 13. 格奥尔基耶娃呼吁释放新兴市场私营部门潜力\n- **时间**: 2026-02-08\n- **来源**: Arab News\n- **摘要**: 据Arab News报道，IMF总裁格奥尔基耶娃在第二届新兴市场会议上提出了促进增长的两大优先级。首先是通过减少行政干预、深化金融市场和强化机构治理来释放私营部门的潜力；其次是加强区域间整合以应对全球贸易格局的变化。她认为，私营部门的活力是新兴经济体实现可持续增长的关键所在。分析人士指出，这一建议为面临结构性改革压力的新兴市场提供了明确的路线图，强调了内部改革与区域合作在应对全球不确定性中的重要性。\n- **消息来源**:\n  - [1] [Arab News](https://www.arabnews.com/node/2632181/business-economy)\n\n### 14. 降息预期或将引导资本回流新兴市场资产\n- **时间**: 2026-02-08\n- **来源**: Bitget\n- **摘要**: 据Bitget发布的市场分析报告指出，随着市场对美联储未来降息的预期逐步升温，美元的强势地位可能面临挑战。在这种背景下，新兴市场资产的吸引力有望得到显著提升，从而引导全球资本重新流入。发回的报道显示，尽管前景乐观，但专家仍警告称，新兴市场必须警惕因汇率波动和全球风险情绪变化带来的资本外流风险。分析认为，新兴经济体需要建立更具韧性的金融体系，以应对由发达国家利率政策转向带来的剧烈资本波动。\n- **消息来源**:\n  - [1] [Bitget](https://www.bitget.com/wiki/how-interest-rate-cuts-affect-stock-market)\n\n### 15. 印度首次向全球投资者开放直接股权投资门槛\n- **时间**: 2026-02-08\n- **来源**: The Banking Updates\n- **摘要**: 据本台消息，印度政府近日发布了一项具有里程碑意义的政策，宣布将首次向全球投资者开放股权市场门槛，允许外国人直接进行股权投资。这一举措旨在显著提振外资流入，并进一步深化印度资本市场。发回的报道指出，在印度政府努力实现经济现代化的进程中，此举被视为吸引全球长期资本的关键一步。市场对此反应热烈，普遍认为这将极大地提升印度股市的国际参与度，并为当地企业提供更多元的融资渠道。本台也将密切关注该政策的具体落地细则。\n- **消息来源**:\n  - [1] [The Banking Updates](https://thebankingupdates.com/)\n\n### 16. 税政变动引发印度股市剧烈波动后强劲反弹\n- **时间**: 2026-02-08\n- **来源**: Partystar.be\n- **摘要**: 据Partystar.be报道，印度资本市场近期经历了一场剧烈的震荡博弈。受2026-27年度预算案提议上调期货与期权（F&O）证券交易税的影响，印度股市在周日一度出现2%的跌幅。然而，在政策不确定性稍微缓解后，Sensex指数随后强劲反弹942点。分析指出，这一现象反映出在新政影响下，多空双方在资本市场进行了激烈的博弈。尽管税收政策调整带来了短期冲击，但市场对印度经济长期增长的信心依然显示出了极强的韧性。\n- **消息来源**:\n  - [1] [Partystar.be](https://partystar.be/6empd8lpc9uqs8)\n\n### 17. 美债10年期收益率触及4.22%反映财政忧虑\n- **时间**: 2026-02-08\n- **来源**: Trading Economics\n- **摘要**: 据Trading Economics发布的最新债市监测，美国10年期国债收益率在2月6日升至4.22%，较前一交易日上涨0.03个百分点。这一显著回升反映出投资者对美国政府财政赤字及未来政策不确定性的日益担忧。发回的分析显示，债券市场正处于敏感期，投资者正重新构建期限溢价，导致收益率曲线进一步陡峭化。这种收益率的上行压力，正随着发达经济体同步降息周期的结束而变得更加明显，市场开始重新评估长期债务的持有成本。\n- **消息来源**:\n  - [1] [Trading Economics](https://tradingeconomics.com/united-states/government-bond-yield)\n\n### 18. 德国央行报告偏鹰派令全球政府债券收益率普涨\n- **时间**: 2026-02-08\n- **来源**: Reuters\n- **摘要**: 据路透社援引德国联邦银行2月6日发布的鹰派报告显示，全球政府债券市场正面临新一波收益率上行压力。报告中对通胀风险的强硬表态，直接带动了英国、日本及加拿大等国债券收益率的集体走高。目前，英国国债收益率已触及4.51%，日本上扬至2.23%，加拿大则报3.41%。观察人士指出，随着财政扩张（如德国增加国防基建投入）逐渐取代货币政策成为波动的主导因素，全球债市正经历一场由财政主导的深刻调整，投资者需警惕由此带来的估值压力。\n- **消息来源**:\n  - [1] [Reuters](https://www.youtube.com/watch?v=SsGWVpyHp4w)\n\n### 19. 分析警告美国财政压力或引发主权违约风险\n- **时间**: 2026-02-07\n- **来源**: Pun Salad\n- **摘要**: 据Pun Salad发布的一份深度分析报告警告称，美国持续攀升的债务规模及财政压力正将整个金融系统推向临界点。如果政治僵局持续阻碍关键的财政改革，公众信心的彻底流失可能导致美元面临突然且大幅贬值的“货币危机”。报告极具冲击力地指出，政策制定者可能被迫面临显性或隐性的债务违约，包括未能按期支付债务或进行强制性重组。这种财政灵活性丧失所带来的长期损害，可能远超以往任何一次急性危机对生活水平的影响。\n- **消息来源**:\n  - [1] [Pun Salad](https://punsalad.com/)\n\n### 20. 日本新内阁财政刺激预期推动国债收益率曲线陡峭化\n- **时间**: 2026-02-08\n- **来源**: Bloomberg (MLIV)\n- **摘要**: 据彭博社（MLIV）最新分析，受日本新内阁可能实施的大规模财政刺激计划影响，日本国债收益率近期呈现显著上行。市场普遍预期，新政府的扩张性财政政策将增加政府融资需求，从而推动收益率曲线进一步陡峭化。目前，10年期日债收益率已升至2.23%。分析人士认为，这一趋势反映出日本正从长期的货币宽松向财政主导型政策转变。由于全球市场的高度联动，日本债市的这种异动也引发了国际资本对避险和套利头寸的重新审视。本台将继续关注其后续发展。\n- **消息来源**:\n  - [1] [Bloomberg (MLIV)](https://www.youtube.com/watch?v=g6bcuytZis8)",
  "audioUrl": "https://storage.dailyintel.qzz.io/zh/economy/audio_2026-02-08.mp3"
}
